pyflowercare/__init__.py
pyflowercare/constants.py
pyflowercare/device.py
pyflowercare/exceptions.py
pyflowercare/logging.py
pyflowercare/models.py
pyflowercare/scanner.py
pyflowercare-0.3.0.dist-info/LICENSE
pyflowercare-0.3.0.dist-info/WHEEL
pyflowercare-0.3.0.dist-info/METADATA
pyflowercare-0.3.0.dist-info/RECORD
