Metadata-Version: 2.1
Name: pyflowercare
Version: 0.3.0
Summary: Python library for communicating with FlowerCare (Xiaomi MiFlora) Bluetooth plant sensors
Home-page: https://github.com/eljhr9/pyflowercare
License: MIT
Keywords: flowercare,xiaomi,miflora,bluetooth,plant,sensor,ble
Author: Ilya Redkolis
Author-email: illyaredkolis@gmail.com
Requires-Python: >=3.9,<3.13
Classifier: Development Status :: 4 - Beta
Classifier: Intended Audience :: Developers
Classifier: License :: OSI Approved :: MIT License
Classifier: Operating System :: OS Independent
Classifier: Programming Language :: Python :: 3
Classifier: Programming Language :: Python :: 3.9
Classifier: Programming Language :: Python :: 3.10
Classifier: Programming Language :: Python :: 3.11
Classifier: Programming Language :: Python :: 3
Classifier: Programming Language :: Python :: 3.10
Classifier: Programming Language :: Python :: 3.11
Classifier: Programming Language :: Python :: 3.12
Classifier: Programming Language :: Python :: 3.9
Classifier: Topic :: Home Automation
Classifier: Topic :: Software Development :: Libraries :: Python Modules
Classifier: Topic :: System :: Hardware :: Hardware Drivers
Requires-Dist: bleak (>=0.21.0,<0.22.0)
Requires-Dist: pydantic (>=2.0.0,<3.0.0)
Project-URL: Repository, https://github.com/eljhr9/pyflowercare
